[
    {
        "type": "message",
        "user": "UA1239MTQ",
        "text": "コモンスペースを次の目的で予約します．\n----------\n日程：6月8日（金）11:30 ～ 12:30\n場所：コモンスペース（KC103）\n目的：研究ミーティング【複合環境班】\n----------\nなお，この予定はGoogleカレンダーに登録致しました．",
        "ts": "1527838573.000022"
    },
    {
        "type": "message",
        "user": "UA1239MTQ",
        "text": "コモンスペースを次の目的で予約します．\n----------\n日程：6月6日（金）13:30 ～ 14:00\n場所：コモンスペース（KC103）\n目的：研究室大改革ミーティング\n----------\nなお，この予定はGoogleカレンダーに登録致しました．",
        "ts": "1527839028.000069"
    }
]